faustprometheus/__init__.py
faustprometheus/config.py
faustprometheus/metrics.py
faustprometheus/monitor.py
tests/__init__.py
tests/test_monitor.py
faustprometheus-0.0.6.dist-info/LICENSE
faustprometheus-0.0.6.dist-info/METADATA
faustprometheus-0.0.6.dist-info/WHEEL
faustprometheus-0.0.6.dist-info/top_level.txt
faustprometheus-0.0.6.dist-info/zip-safe
faustprometheus-0.0.6.dist-info/RECORD
