Metadata-Version: 2.1
Name: faustprometheus
Version: 0.0.6
Summary: WoodMac's Faust Prometheus Library
Home-page: https://github.com/woodmac/faust-prometheus
Author: Wood Mackenzie
Author-email: mr.kecskes@gmail.com
License: UNKNOWN
Platform: UNKNOWN
Classifier: Programming Language :: Python :: 3.6
Classifier: License :: OSI Approved :: BSD License
Classifier: Operating System :: OS Independent
Classifier: Development Status :: 5 - Production/Stable
Classifier: Topic :: System :: Monitoring
Requires-Python: >=3.6
License-File: LICENSE
Requires-Dist: faust (~=1.10.4)
Requires-Dist: pytest
Requires-Dist: prometheus-client
